[
  {
    "ContainingType": "server.Controllers.AuthController",
    "Method": "Login",
    "RelativePath": "Auth/login",
    "HttpMethod": "POST",
    "IsController": true,
    "Order": 0,
    "Parameters": [
      {
        "Name": "loginDto",
        "Type": "server.Models.LoginDto",
        "IsRequired": true
      }
    ],
    "ReturnTypes": []
  },
  {
    "ContainingType": "server.Controllers.AuthController",
    "Method": "Signup",
    "RelativePath": "Auth/signup",
    "HttpMethod": "POST",
    "IsController": true,
    "Order": 0,
    "Parameters": [
      {
        "Name": "signupDto",
        "Type": "server.Models.SignupDto",
        "IsRequired": true
      }
    ],
    "ReturnTypes": []
  },
  {
    "ContainingType": "server.Controllers.AuthController",
    "Method": "UserEmailExist",
    "RelativePath": "Auth/useremailexist",
    "HttpMethod": "POST",
    "IsController": true,
    "Order": 0,
    "Parameters": [
      {
        "Name": "userEmailExistDto",
        "Type": "server.Models.UserEmailExistDto",
        "IsRequired": true
      }
    ],
    "ReturnTypes": []
  },
  {
    "ContainingType": "server.Controllers.AuthController",
    "Method": "UsernameExist",
    "RelativePath": "Auth/usernameexist",
    "HttpMethod": "POST",
    "IsController": true,
    "Order": 0,
    "Parameters": [
      {
        "Name": "usernameExistDto",
        "Type": "server.Models.UsernameExistDto",
        "IsRequired": true
      }
    ],
    "ReturnTypes": []
  },
  {
    "ContainingType": "server.Controllers.PostsController",
    "Method": "GetAllPosts",
    "RelativePath": "Posts",
    "HttpMethod": "GET",
    "IsController": true,
    "Order": 0,
    "Parameters": [],
    "ReturnTypes": []
  },
  {
    "ContainingType": "server.Controllers.PostsController",
    "Method": "AddPost",
    "RelativePath": "Posts/addposts",
    "HttpMethod": "POST",
    "IsController": true,
    "Order": 0,
    "Parameters": [
      {
        "Name": "UserId",
        "Type": "System.Guid",
        "IsRequired": false
      },
      {
        "Name": "Feeds",
        "Type": "System.Collections.Generic.List\u00601[[System.String, System.Private.CoreLib, Version=8.0.0.0, Culture=neutral, PublicKeyToken=7cec85d7bea7798e]]",
        "IsRequired": false
      }
    ],
    "ReturnTypes": []
  },
  {
    "ContainingType": "server.Controllers.UsersController",
    "Method": "GetAllUsers",
    "RelativePath": "Users",
    "HttpMethod": "GET",
    "IsController": true,
    "Order": 0,
    "Parameters": [],
    "ReturnTypes": []
  },
  {
    "ContainingType": "server.Controllers.UsersController",
    "Method": "UpdateUser",
    "RelativePath": "Users",
    "HttpMethod": "PUT",
    "IsController": true,
    "Order": 0,
    "Parameters": [
      {
        "Name": "Name",
        "Type": "System.String",
        "IsRequired": false
      },
      {
        "Name": "ProfileImage",
        "Type": "System.String",
        "IsRequired": false
      },
      {
        "Name": "Bio",
        "Type": "System.String",
        "IsRequired": false
      },
      {
        "Name": "UserId",
        "Type": "System.Guid",
        "IsRequired": false
      }
    ],
    "ReturnTypes": []
  },
  {
    "ContainingType": "server.Controllers.UsersController",
    "Method": "GetUserById",
    "RelativePath": "Users/{id}",
    "HttpMethod": "GET",
    "IsController": true,
    "Order": 0,
    "Parameters": [
      {
        "Name": "id",
        "Type": "System.Guid",
        "IsRequired": true
      }
    ],
    "ReturnTypes": []
  },
  {
    "ContainingType": "server.Controllers.UsersController",
    "Method": "DeleteUser",
    "RelativePath": "Users/{id}",
    "HttpMethod": "DELETE",
    "IsController": true,
    "Order": 0,
    "Parameters": [
      {
        "Name": "id",
        "Type": "System.Guid",
        "IsRequired": true
      }
    ],
    "ReturnTypes": []
  },
  {
    "ContainingType": "server.Controllers.UsersController",
    "Method": "FollowUser",
    "RelativePath": "Users/follow",
    "HttpMethod": "PUT",
    "IsController": true,
    "Order": 0,
    "Parameters": [
      {
        "Name": "followerDto",
        "Type": "server.Models.FollowerDto",
        "IsRequired": true
      }
    ],
    "ReturnTypes": []
  },
  {
    "ContainingType": "server.Controllers.UsersController",
    "Method": "UnfollowUser",
    "RelativePath": "Users/unfollow",
    "HttpMethod": "PUT",
    "IsController": true,
    "Order": 0,
    "Parameters": [
      {
        "Name": "followerDto",
        "Type": "server.Models.FollowerDto",
        "IsRequired": true
      }
    ],
    "ReturnTypes": []
  }
]